Workbook

Sheet DCF
A1: Last Modified 2/9/2026 | E1: Tesla Inc. (TSLA) | H1: Mohanad Assali
A2: DCF
E6: Annually
A7: DCF Model
A8: $millions | C8: 5-year FCF Model
E9: FY2026 | F9: FY2027 | G9: FY2028 | H9: FY2029 | I9: FY2030
C10: Net Revenue | E10: 107800 | F10: 118580 | G10: 130438 | H10: 143481.8 | I10: 157829.98
C11: EBITDA | E11: 9633.2 | F11: 10646.52 | G11: 11761.172 | H11: 12987.289 | I11: 14336.018
C12: D&A | E12: 5390 | F12: 5929 | G12: 6521.9 | H12: 7174.09 | I12: 7891.499
C13: EBIT | E13: =E11-E12 -> 4243.2 | F13: =F11-F12 -> 4717.52 | G13: =G11-G12 -> 5239.272 | H13: =H11-H12 -> 5813.1992 | I13: =I11-I12 -> 6444.5191
C14: Taxes | E14: =E13*'WAAC & Assumptions'!$D$23 -> 891.072 | F14: =F13*'WAAC & Assumptions'!$D$23 -> 990.6792 | G14: =G13*'WAAC & Assumptions'!$D$23 -> 1100.2471 | H14: =H13*'WAAC & Assumptions'!$D$23 -> 1220.7718 | I14: =I13*'WAAC & Assumptions'!$D$23 -> 1353.349
C15: NOPAT | E15: =E13-E14 -> 3352.128 | F15: =F13-F14 -> 3726.8408 | G15: =G13-G14 -> 4139.0249 | H15: =H13-H14 -> 4592.4274 | I15: =I13-I14 -> 5091.1701
C16: D&A | E16: =E10*'WAAC & Assumptions'!$D$25 -> 5390 | F16: =F10*'WAAC & Assumptions'!$D$25 -> 5929 | G16: =G10*'WAAC & Assumptions'!$D$25 -> 6521.9 | H16: =H10*'WAAC & Assumptions'!$D$25 -> 7174.09 | I16: =I10*'WAAC & Assumptions'!$D$25 -> 7891.499
C17: CapEx | E17: =E10*'WAAC & Assumptions'!$D$24 -> 3234 | F17: =F10*'WAAC & Assumptions'!$D$24 -> 3557.4 | G17: =G10*'WAAC & Assumptions'!$D$24 -> 3913.14 | H17: =H10*'WAAC & Assumptions'!$D$24 -> 4304.454 | I17: =I10*'WAAC & Assumptions'!$D$24 -> 4734.8994
C18: WC | E18: 196 | F18: 215.6 | G18: 237.16 | H18: 260.876 | I18: 286.9636
C19: Unlevered FCF | E19: 5000 | F19: 3511.2408 | G19: 3901.8649 | H19: 4331.5514 | I19: 4804.2065
C21: DCF Summary Table
A22: 5-year forecast | C22: Discount period | E22: 1 | F22: 2 | G22: 3 | H22: 4 | I22: 5
C23: PV | E23: =E19*(1+'WAAC & Assumptions'!D19)^E22 -> 5525.7054 | F23: =F19*(1+'WAAC & Assumptions'!D19)^F22 -> 4288.4077 | G23: =G19*(1+'WAAC & Assumptions'!D19)^G22 -> 5266.5402 | H23: =H19*(1+'WAAC & Assumptions'!D19)^H22 -> 6461.2177 | I23: =I19*(1+'WAAC & Assumptions'!D19)^I22 -> 7919.7286
C24: Total Stage1 PV | E24: =SUM(E23:I23) -> 29461.6
A26: Terminal Value | C26: Terminal Year FCF | D26: =I19*(1+'WAAC & Assumptions'!D22) -> 4948.3327
C27: Terminal Value | D27: =D26/('WAAC & Assumptions'!D19-'WAAC & Assumptions'!D22) -> 65853.886
C28: Discount Factor | D28: =1/((1+'WAAC & Assumptions'!D22)^I22) -> 0.86260878
C29: PV of Terminal Value | D29: =D27*D28 -> 56806.141
C31: Total Enterprise Value | D31: =E24+D29 -> 86267.74
A35: Share Price | C35: EV | D35: =D31 -> 86267.74
C36: Cash | D36: 44059 | E36: FY2025
C37: Debt | D37: 8213 | E37: Debt
C38: Equity Value | D38: =D35+D36-D37 -> 122113.74
C39: Shares Outstanding | D39: 3498
C40: Intrinsic Share Price

Sheet WAAC & Assumptions
D1: Tesla Inc. (TSLA)
A2: WAAC
A7: WAAC Calculation
C8: MC | D8: 1393605
C9: Debt | D9: 8213
C10: Total Capital | D10: 1401818
C11: %Equity | D11: 0.99414118
C12: %Debt | D12: 0.0058588205
C13: Risk Free Rate (EFP) | D13: 0.0428
C14: Beta | D14: 1.5
C15: Equity Risk Premium (ERP) | D15: 0.0418 | E15: (Damodaran/JPM)
C16: Cost of Equity | D16: 0.1055
C17: Cost of Debt | D17: 0.056
C18: Tax Rate | D18: 0.21
C19: WAAC | D19: =(D11*D16)+(D12*D17*(1-D18)) -> 0.10514109
A22: Assumptions | C22: G | D22: 0.03
C23: Tax | D23: 0.21
C24: Capex | D24: 0.03
C25: D&A | D25: 0.05
C26: WC | D26: 0.02

Sheet Important Notes
D1: Tesla Inc. (TSLA)
A2: Notes
C3: Refer to ''Capital Structure_Financial Statements'' Excel File
C4: A fully linked model is available.
C5: Tesla Share price valuation is flawed. Will optimize projection techniques in the upcoming model
