Workbook

Sheet Comps
A2: Comps
F8: Last Twelve Months (LTM) | K8: Year 1 Forecast - Calendar Year | P8: Year 2 Forecast - Calendar Year
B9: Ticker | C9: Market capitalization (mm) | D9: Enterprise value (EV) | F9: Revenues | G9: EBITDA | H9: EBIT | I9: EPS | K9: Revenues | L9: EBITDA | M9: EBIT | N9: EPS | P9: Revenues | Q9: EBITDA | R9: EBIT | S9: EPS | T9: LT growth rate
B11: =CompsInputs!D$10 -> META | C11: =CompsInputs!D21*CompsInputs!D13 -> 1671933 | D11: =CompsInputs!D139+CompsInputs!D131 -> 1651024 | F11: =CompsInputs!D29+CompsInputs!D46-CompsInputs!D63 -> 212473 | G11: =CompsInputs!D42+CompsInputs!D59-CompsInputs!D76 -> 117428 | H11: =CompsInputs!D34+CompsInputs!D51-CompsInputs!D68 -> 84656 | I11: =CompsInputs!D39+CompsInputs!D56-CompsInputs!D73 -> 26.409986 | K11: =CompsInputs!D101 -> 249400 | L11: =CompsInputs!D102 -> 126800 | M11: =CompsInputs!D103 -> 98500 | N11: =CompsInputs!D104 -> 29.56 | P11: =CompsInputs!D110 -> 301300 | Q11: =CompsInputs!D111 -> 158200 | R11: =CompsInputs!D112 -> 123500 | S11: =CompsInputs!D113 -> 35.23 | T11: =CompsInputs!D118 -> 0.225
B12: =CompsInputs!E$10 -> GOOGL | C12: =CompsInputs!E21*CompsInputs!E13 -> 2372292 | D12: =CompsInputs!E139+CompsInputs!E131 -> 2300296 | F12: =CompsInputs!E29+CompsInputs!E46-CompsInputs!E63 -> 406167 | G12: =CompsInputs!E42+CompsInputs!E59-CompsInputs!E76 -> 146855 | H12: =CompsInputs!E34+CompsInputs!E51-CompsInputs!E68 -> 129805 | I12: =CompsInputs!E39+CompsInputs!E56-CompsInputs!E73 -> 8.95 | K12: =CompsInputs!E101 -> 448500 | L12: =CompsInputs!E102 -> 162100 | M12: =CompsInputs!E103 -> 141300 | N12: =CompsInputs!E104 -> 12.45 | P12: =CompsInputs!E110 -> 506800 | Q12: =CompsInputs!E111 -> 188000 | R12: =CompsInputs!E112 -> 163900 | S12: =CompsInputs!E113 -> 14.2 | T12: =CompsInputs!E118 -> 0.182
B13: =CompsInputs!F$10 -> SNAP | C13: =CompsInputs!F21*CompsInputs!F13 -> 21748.5 | D13: =CompsInputs!F139+CompsInputs!F131 -> 22842.5 | F13: =CompsInputs!F29+CompsInputs!F46-CompsInputs!F63 -> 6090 | G13: =CompsInputs!F42+CompsInputs!F59-CompsInputs!F76 -> 684 | H13: =CompsInputs!F34+CompsInputs!F51-CompsInputs!F68 -> -455 | I13: =CompsInputs!F39+CompsInputs!F56-CompsInputs!F73 -> -0.25 | K13: =CompsInputs!F101 -> 7250 | L13: =CompsInputs!F102 -> 940 | M13: =CompsInputs!F103 -> -420 | N13: =CompsInputs!F104 -> -0.05 | P13: =CompsInputs!F110 -> 8100 | Q13: =CompsInputs!F111 -> 1250 | R13: =CompsInputs!F112 -> 210 | S13: =CompsInputs!F113 -> 0.12 | T13: =CompsInputs!F118 -> 0.24
B14: =CompsInputs!G$10 -> MSFT | C14: =CompsInputs!G21*CompsInputs!G13 -> 3658408 | D14: =CompsInputs!G139+CompsInputs!G131 -> 3616973 | F14: =CompsInputs!G29+CompsInputs!G46-CompsInputs!G63 -> 288533 | G14: =CompsInputs!G42+CompsInputs!G59-CompsInputs!G76 -> 152167 | H14: =CompsInputs!G34+CompsInputs!G51-CompsInputs!G68 -> 131217 | I14: =CompsInputs!G39+CompsInputs!G56-CompsInputs!G73 -> 14.06 | K14: =CompsInputs!G101 -> 332100 | L14: =CompsInputs!G102 -> 178400 | M14: =CompsInputs!G103 -> 152600 | N14: =CompsInputs!G104 -> 16.8 | P14: =CompsInputs!G110 -> 386700 | Q14: =CompsInputs!G111 -> 208800 | R14: =CompsInputs!G112 -> 179200 | S14: =CompsInputs!G113 -> 19.44 | T14: =CompsInputs!G118 -> 0.175
F16: Last Twelve Months (LTM) | K16: Year 1 Forecast - Calendar Year | P16: Year 2 Forecast - Calendar Year
B17: Ticker | F17: EV / Revenues | G17: EV / EBITDA | H17: EV / EBIT | I17: P/E | K17: EV / Revenues | L17: EV / EBITDA | M17: EV / EBIT | N17: P/E | P17: EV / Revenues | Q17: EV / EBITDA | R17: EV / EBIT | S17: P/E | T17: PEG ratio
B19: =CompsInputs!D$10 -> META | F19: =CompsInputs!D142/CompsInputs!D83 -> 8.2154803 | G19: =CompsInputs!D142/CompsInputs!D84 -> 16.203826 | H19: =CompsInputs!D142/CompsInputs!D85 -> 19.826166 | I19: =CompsInputs!D13/CompsInputs!D86 -> 25.660552 | K19: =CompsInputs!D$142/CompsInputs!D101 -> 6.619984 | L19: =CompsInputs!D$142/CompsInputs!D102 -> 13.020694 | M19: =CompsInputs!D$142/CompsInputs!D103 -> 16.761665 | N19: =CompsInputs!D137/CompsInputs!D104 -> 22.18065 | P19: =CompsInputs!D$142/CompsInputs!D110 -> 5.4796681 | Q19: =CompsInputs!D$142/CompsInputs!D111 -> 10.436308 | R19: =CompsInputs!D$142/CompsInputs!D112 -> 13.368615 | S19: =CompsInputs!D137/CompsInputs!D113 -> 18.610843 | T19: =CompsInputs!D155/(CompsInputs!D118*100) -> 0.98580665
B20: =CompsInputs!E$10 -> GOOGL | F20: =CompsInputs!E142/CompsInputs!E83 -> 5.7102543 | G20: =CompsInputs!E142/CompsInputs!E84 -> 15.702751 | H20: =CompsInputs!E142/CompsInputs!E85 -> 17.826224 | I20: =CompsInputs!E13/CompsInputs!E86 -> 22.850356 | K20: =CompsInputs!E$142/CompsInputs!E101 -> 5.1288651 | L20: =CompsInputs!E$142/CompsInputs!E102 -> 14.190598 | M20: =CompsInputs!E$142/CompsInputs!E103 -> 16.279519 | N20: =CompsInputs!E137/CompsInputs!E104 -> 15.453815 | P20: =CompsInputs!E$142/CompsInputs!E110 -> 4.5388635 | Q20: =CompsInputs!E$142/CompsInputs!E111 -> 12.235617 | R20: =CompsInputs!E$142/CompsInputs!E112 -> 14.034753 | S20: =CompsInputs!E137/CompsInputs!E113 -> 13.549296 | T20: =CompsInputs!E155/(CompsInputs!E118*100) -> 0.84911073
B21: =CompsInputs!F$10 -> SNAP | F21: =CompsInputs!F142/CompsInputs!F83 -> 3.8513741 | G21: =CompsInputs!F142/CompsInputs!F84 -> 33.15312 | H21: =CompsInputs!F142/CompsInputs!F85 -> -42.93703 | I21: =CompsInputs!F13/CompsInputs!F86 -> -45 | K21: =CompsInputs!F$142/CompsInputs!F101 -> 3.1506897 | L21: =CompsInputs!F$142/CompsInputs!F102 -> 24.300532 | M21: =CompsInputs!F$142/CompsInputs!F103 -> -54.386905 | N21: =CompsInputs!F137/CompsInputs!F104 -> -243 | P21: =CompsInputs!F$142/CompsInputs!F110 -> 2.8200617 | Q21: =CompsInputs!F$142/CompsInputs!F111 -> 18.274 | R21: =CompsInputs!F$142/CompsInputs!F112 -> 108.77381 | S21: =CompsInputs!F137/CompsInputs!F113 -> 101.25 | T21: =CompsInputs!F155/(CompsInputs!F118*100) -> -10.125
B22: =CompsInputs!G$10 -> MSFT | F22: =CompsInputs!G142/CompsInputs!G83 -> 11.599889 | G22: =CompsInputs!G142/CompsInputs!G84 -> 21.38778 | H22: =CompsInputs!G142/CompsInputs!G85 -> 25.368915 | I22: =CompsInputs!G13/CompsInputs!G86 -> 29.264174 | K22: =CompsInputs!G$142/CompsInputs!G101 -> 10.891217 | L22: =CompsInputs!G$142/CompsInputs!G102 -> 20.274512 | M22: =CompsInputs!G$142/CompsInputs!G103 -> 23.702313 | N22: =CompsInputs!G137/CompsInputs!G104 -> 28.880952 | P22: =CompsInputs!G$142/CompsInputs!G110 -> 9.3534342 | Q22: =CompsInputs!G$142/CompsInputs!G111 -> 17.322668 | R22: =CompsInputs!G$142/CompsInputs!G112 -> 20.184001 | S22: =CompsInputs!G137/CompsInputs!G113 -> 24.958848 | T22: =CompsInputs!G155/(CompsInputs!G118*100) -> 1.6503401
E24: High | F24: =MAX(F19:F22) -> 11.599889 | G24: =MAX(G19:G22) -> 33.15312 | H24: =MAX(H19:H22) -> 25.368915 | I24: =MAX(I19:I22) -> 29.264174 | K24: =MAX(K19:K22) -> 10.891217 | L24: =MAX(L19:L22) -> 24.300532 | M24: =MAX(M19:M22) -> 23.702313 | N24: =MAX(N19:N22) -> 28.880952 | P24: =MAX(P19:P22) -> 9.3534342 | Q24: =MAX(Q19:Q22) -> 18.274 | R24: =MAX(R19:R22) -> 108.77381 | S24: =MAX(S19:S22) -> 101.25 | T24: =MAX(T19:T22) -> 1.6503401
E25: Low | F25: =MIN(F19:F22) -> 3.8513741 | G25: =MIN(G19:G22) -> 15.702751 | H25: =MIN(H19:H22) -> -42.93703 | I25: =MIN(I19:I22) -> -45 | K25: =MIN(K19:K22) -> 3.1506897 | L25: =MIN(L19:L22) -> 13.020694 | M25: =MIN(M19:M22) -> -54.386905 | N25: =MIN(N19:N22) -> -243 | P25: =MIN(P19:P22) -> 2.8200617 | Q25: =MIN(Q19:Q22) -> 10.436308 | R25: =MIN(R19:R22) -> 13.368615 | S25: =MIN(S19:S22) -> 13.549296 | T25: =MIN(T19:T22) -> -10.125
E26: Median | F26: =MEDIAN(F19:F22) -> 6.9628673 | G26: =MEDIAN(G19:G22) -> 18.795803 | H26: =MEDIAN(H19:H22) -> 18.826195 | I26: =MEDIAN(I19:I22) -> 24.255454 | K26: =MEDIAN(K19:K22) -> 5.8744245 | L26: =MEDIAN(L19:L22) -> 17.232555 | M26: =MEDIAN(M19:M22) -> 16.520592 | N26: =MEDIAN(N19:N22) -> 18.817232 | P26: =MEDIAN(P19:P22) -> 5.0092658 | Q26: =MEDIAN(Q19:Q22) -> 14.779142 | R26: =MEDIAN(R19:R22) -> 17.109377 | S26: =MEDIAN(S19:S22) -> 21.784845 | T26: =MEDIAN(T19:T22) -> 0.91745869
E27: Mean | F27: =AVERAGE(F19:F22) -> 7.3442494 | G27: =AVERAGE(G19:G22) -> 21.611869 | H27: =AVERAGE(H19:H22) -> 5.0210688 | I27: =AVERAGE(I19:I22) -> 8.1937705 | K27: =AVERAGE(K19:K22) -> 6.4476888 | L27: =AVERAGE(L19:L22) -> 17.946584 | M27: =AVERAGE(M19:M22) -> 0.58914805 | N27: =AVERAGE(N19:N22) -> -44.121146 | P27: =AVERAGE(P19:P22) -> 5.5480069 | Q27: =AVERAGE(Q19:Q22) -> 14.567148 | R27: =AVERAGE(R19:R22) -> 39.090295 | S27: =AVERAGE(S19:S22) -> 39.592247 | T27: =AVERAGE(T19:T22) -> -1.6599356
B28: =CompsInputs!$D$10 -> META | E28: EXTR | F28: =F19 -> 8.2154803 | G28: =G19 -> 16.203826 | H28: =H19 -> 19.826166 | I28: =I19 -> 25.660552 | K28: =K19 -> 6.619984 | L28: =L19 -> 13.020694 | M28: =M19 -> 16.761665 | N28: =N19 -> 22.18065 | P28: =P19 -> 5.4796681 | Q28: =Q19 -> 10.436308 | R28: =R19 -> 13.368615 | S28: =S19 -> 18.610843 | T28: =T19 -> 0.98580665

Sheet CompsInputs
N1: Ticker | O1: Name
A2: CompsInputs | N2: GOOGL | O2: Alphabet Inc. | P2: Primary Ad Competitor
N3: SNAP | O3: Snap Inc. | P3: Social Media Peer
N4: MSFT | O4: Microsoft | P4: AI / Infrastructure Peer
C8: Market Data Inputs
D9: 1 | E9: 2 | F9: 3 | G9: 4 | H9: 5 | I9: 6
C10: Ticker | D10: META | E10: GOOGL | F10: SNAP | G10: MSFT
C11: Date of latest filing | D11: 46051 | E11: 46055 | F11: 46058 | G11: 46049
C12: Date of latest fiscal year end (FYE) | D12: 46022 | E12: 46022 | F12: 46022 | G12: 45838
C13: Stock price on current date | D13: 655.66 | E13: 192.4 | F13: 12.15 | G13: 485.2
C14: Share price date | D14: 46075 | E14: 46075 | F14: 46075 | G14: 46075
C16: Shares Data
C17: Basic shares outstanding | D17: 2510 | E17: 12150 | F17: 1650 | G17: 7430
C18: Net shares from exercisable options | D18: 40 | E18: 180 | F18: 95 | G18: 110
C19: Total shares from convertible debt | D19: 0 | E19: 0 | F19: 45 | G19: 0
C20: Total shares from convertible preferred stock | D20: 0 | E20: 0 | F20: 0 | G20: 0
C21: Fully diluted shares | D21: 2550 | E21: =SUM(E17:E20) -> 12330 | F21: =SUM(F17:F20) -> 1790 | G21: =SUM(G17:G20) -> 7540
C25: Financials
C27: LAST FISCAL YEAR
D28: META | E28: =E$10 -> GOOGL | F28: =F$10 -> SNAP | G28: =G$10 -> MSFT | H28: =H$10 -> 0 | I28: =I$10 -> 0
C29: Revenues | D29: 200965 | E29: 402836 | F29: 5931 | G29: 281724
C30: COGS | D30: 36175 | E30: 134846 | F30: 2720 | G30: 87830
C31: Gross Profit | D31: 164790 | E31: =E29-E30 -> 267990 | F31: =F29-F30 -> 3211 | G31: =G29-G30 -> 193894
C32: R&D | D32: 57372 | E32: 52140 | F32: 1765 | G32: 32800
C33: SG&A | D33: 24143 | E33: 86810 | F33: 1978 | G33: 32566
C34: EBIT | D34: 83275 | E34: =E31-E32-E33 -> 129040 | F34: =F31-F32-F33 -> -532 | G34: =G31-G32-G33 -> 128528
C35: Interest expense | D35: 2656 | E35: 3450 | F35: -122 | G35: 1020
C36: Pretax income | D36: 85931 | E36: =SUM(E34:E35) -> 132490 | F36: =SUM(F34:F35) -> -654 | G36: =SUM(G34:G35) -> 129548
C37: Taxes (Benefit) | D37: 20162 | E37: 26498 | F37: 9 | G37: 27716
C38: Net Income | D38: 65769 | E38: =E36-E37 -> 105992 | F38: =F36-F37 -> -663 | G38: =G36-G37 -> 101832
C39: Diluted EPS | D39: 25.551282 | E39: 8.42 | F39: -0.27 | G39: 13.64
C41: D&A | D41: 18616 | E41: 17450 | F41: 1221 | G41: 21500
C42: EBITDA | D42: 101891 | E42: =E34+E41 -> 146490 | F42: =F34+F41 -> 689 | G42: =G34+G41 -> 150028
C44: LAST QUARTER
D45: META | E45: =E$10 -> GOOGL | F45: =F$10 -> SNAP | G45: =G$10 -> MSFT | H45: =H$10 -> 0 | I45: =I$10 -> 0
C46: Revenues | D46: 59893 | E46: 99800 | F46: 1716 | G46: 76441
C47: COGS | D47: 10906 | E47: 42914 | F47: 703 | G47: 23697
C48: Gross Profit | D48: 48987 | E48: =E46-E47 -> 56886 | F48: =F46-F47 -> 1013 | G48: =G46-G47 -> 52744
C49: R&D | D49: 17136 | E49: 14037 | F49: 245 | G49: 6412
C50: SG&A | D50: 7107 | E50: 11112 | F50: 718 | G50: 11990
C51: EBIT | D51: 24744 | E51: =E48-E49-E50 -> 31737 | F51: =F48-F49-F50 -> 50 | G51: =G48-G49-G50 -> 34342
C52: Interest expense | D52: 608 | E52: -525 | F52: -11 | G52: -1225
C53: Pretax income | D53: 25352 | E53: =SUM(E51:E52) -> 31212 | F53: =SUM(F51:F52) -> 39 | G53: =SUM(G51:G52) -> 33117
C54: Taxes (Benefit) | D54: 2586 | E54: 7446 | F54: 21 | G54: 6382
C55: Net Income | D55: 27938 | E55: =SUM(E53:E54) -> 38658 | F55: =SUM(F53:F54) -> 60 | G55: =SUM(G53:G54) -> 39499
C56: Diluted EPS | D56: 8.8756335 | E56: 2.68 | F56: 0.03 | G56: 3.65
C58: D&A | D58: 18616 | E58: 4100 | F58: 38 | G58: 4550
C59: EBITDA | D59: 43360 | E59: =E51+E58 -> 35837 | F59: =F51+F58 -> 88 | G59: =G51+G58 -> 38892
C61: LAST QUARTER MINUS 1
D62: META | E62: =E$10 -> GOOGL | F62: =F$10 -> SNAP | G62: =G$10 -> MSFT | H62: =H$10 -> 0 | I62: =I$10 -> 0
C63: Revenues | D63: 48385 | E63: 96469 | F63: 1557 | G63: 69632
C64: COGS | D64: 8839 | E64: 14848 | F64: 654 | G64: 21799
C65: Gross Profit | D65: 39546 | E65: =E63-E64 -> 81621 | F65: =F63-F64 -> 903 | G65: =G63-G64 -> 47833
C66: R&D | D66: 12180 | E66: 12500 | F66: 296 | G66: 7917
C67: SG&A | D67: 4003 | E67: 38149 | F67: 634 | G67: 8263
C68: EBIT | D68: 23363 | E68: =E65-E66-E67 -> 30972 | F68: =F65-F66-F67 -> -27 | G68: =G65-G66-G67 -> 31653
C69: Interest expense | D69: 188 | E69: 1271 | F69: -11 | G69: -2288
C70: Pretax income | D70: 23551 | E70: =SUM(E68:E69) -> 32243 | F70: =SUM(F68:F69) -> -38 | G70: =SUM(G68:G69) -> 29365
C71: Taxes (Benefit) | D71: 2715 | E71: 5707 | F71: -47 | G71: 5257
C72: Net Income | D72: 26266 | E72: =SUM(E70:E71) -> 37950 | F72: =SUM(F70:F71) -> -85 | G72: =SUM(G70:G71) -> 34622
C73: Diluted EPS | D73: 8.0169296 | E73: 2.15 | F73: 0.01 | G73: 3.23
C75: D&A | D75: 4460 | E75: 4500 | F75: 120 | G75: 5100
C76: EBITDA | D76: 27823 | E76: =E68+E75 -> 35472 | F76: =F68+F75 -> 93 | G76: =G68+G75 -> 36753
C78: LTM & LFY
C80: LAST TWELVE MONTHS (LTM)
D81: META | E81: =E$10 -> GOOGL | F81: =F$10 -> SNAP | G81: =G$10 -> MSFT | H81: =H$10 -> 0 | I81: =I$10 -> 0
C82: LTM ending date: | D82: 46022 | E82: 46022 | F82: 46022 | G82: 46022
C83: Revenues - LTM | D83: 200965 | E83: =E29 -> 402836 | F83: =F29 -> 5931 | G83: 311811
C84: EBITDA - LTM | D84: 101891 | E84: =E42 -> 146490 | F84: =F42 -> 689 | G84: 169114
C85: EBIT - LTM | D85: 83275 | E85: =E34 -> 129040 | F85: =F34 -> -532 | G85: 142575
C86: EPS - LTM | D86: 25.551282 | E86: =E39 -> 8.42 | F86: =F39 -> -0.27 | G86: 16.58
C88: LAST FISCAL YEAR
D89: META | E89: =E$10 -> GOOGL | F89: =F$10 -> SNAP | G89: =G$10 -> MSFT | H89: =H$10 -> 0 | I89: =I$10 -> 0
C90: Year ending date | D90: 46022 | E90: 46022 | F90: 46022 | G90: 46022
C91: Revenues - latest FYE | D91: 200965 | E91: =E29 -> 402836 | F91: =F29 -> 5931 | G91: =G29 -> 281724
C92: EBITDA - latest FYE | D92: 101891 | E92: =E42 -> 146490 | F92: =F42 -> 689 | G92: =G42 -> 150028
C93: EBIT - latest FYE | D93: 83275 | E93: =E34 -> 129040 | F93: =F34 -> -532 | G93: =G34 -> 128528
C94: EPS - latest FYE | D94: 25.551282 | E94: =E39 -> 8.42 | F94: =F39 -> -0.27 | G94: =G39 -> 13.64
C96: S&P/CIQ Forecast
C98: YEAR 1 FORECAST - CALENDAR YEAR
D99: META | E99: =E$10 -> GOOGL | F99: =F$10 -> SNAP | G99: =G$10 -> MSFT | H99: =H$10 -> 0 | I99: =I$10 -> 0
C100: Year ending date | D100: 46387 | E100: 46387 | F100: 46387 | G100: 46387
C101: Revenues - Year 1 | D101: 249400 | E101: 448500 | F101: 7250 | G101: 332100
C102: EBITDA - Year 1 | D102: 126800 | E102: 162100 | F102: 940 | G102: 178400
C103: EBIT - Year 1 | D103: 98500 | E103: 141300 | F103: -420 | G103: 152600
C104: EPS - Year 1 | D104: 29.56 | E104: 12.45 | F104: -0.05 | G104: 16.8
C105: Source for estimates: | D105: S&P/CIQ
C107: YEAR 2 FORECAST - CALENDAR YEAR
D108: META | E108: =E$10 -> GOOGL | F108: =F$10 -> SNAP | G108: =G$10 -> MSFT | H108: =H$10 -> 0 | I108: =I$10 -> 0
C109: Year ending date | D109: 46752 | E109: 46752 | F109: 46752 | G109: 46752
C110: Revenues - Year 2 | D110: 301300 | E110: 506800 | F110: 8100 | G110: 386700
C111: EBITDA - Year 2 | D111: 158200 | E111: 188000 | F111: 1250 | G111: 208800
C112: EBIT - Year 2 | D112: 123500 | E112: 163900 | F112: 210 | G112: 179200
C113: EPS - Year 2 | D113: 35.23 | E113: 14.2 | F113: 0.12 | G113: 19.44
C114: Source for estimates: | D114: S&P/CIQ
C116: LONG TERM (5 YEAR) GROWTH RATE
D117: META | E117: =E$10 -> GOOGL | F117: =F$10 -> SNAP | G117: =G$10 -> MSFT | H117: =H$10 -> 0 | I117: =I$10 -> 0
C118: Long-term growth rate | D118: 0.225 | E118: 0.182 | F118: 0.24 | G118: 0.175
C119: Source for estimates: | D119: S&P/CIQ
C122: Balance Sheet Data
...
