Workbook
Name Inv_Cap: [1]Results!$E$182:$AD$182
Name NOPLAT: [1]Results!$E$145:$AD$145
Name One: '[1]Forecast Drivers'!$D$330
Name Products: [2]Array0!$B$5:$C$7
Name Rev: '[1]Forecast Drivers'!$E$25:$S$25

Sheet BoostToolkitClipBoard2010
A1: -12

Sheet Outputs
A1: last modified 1/27/2026 | H1: Comps Analysis | O1: Mohanad Assali
A2: Outputs
F8: Last Twelve Months (LTM) | K8: Year 1 Forecast - Calendar Year | P8: Year 2 Forecast - Calendar Year
B9: Ticker | C9: Market capitalization (mm) | D9: Enterprise value (EV) | F9: Revenues | G9: EBITDA | H9: EBIT | I9: EPS | K9: Revenues | L9: EBITDA | M9: EBIT | N9: EPS | P9: Revenues | Q9: EBITDA | R9: EBIT | S9: EPS | T9: LT growth rate
B11: =Inputs!E$8 -> PEP | C11: =Inputs!E19*Inputs!E11 -> 201711.4 | D11: =Inputs!E135+Inputs!E127 -> 241929.4 | F11: =Inputs!E25+Inputs!E43-Inputs!E61 -> 93064 | G11: =Inputs!E40+Inputs!E58-Inputs!E76 -> 18042 | H11: =Inputs!E30+Inputs!E48-Inputs!E66 -> 15227 | I11: =Inputs!E37+Inputs!E55-Inputs!E73 -> 7.93 | K11: =Inputs!E99 -> 98280 | L11: =Inputs!E100 -> 16850 | M11: =Inputs!E101 -> 13970 | N11: =Inputs!E102 -> 8.75 | P11: =Inputs!E108 -> 102150 | Q11: =Inputs!E109 -> 17920 | R11: =Inputs!E110 -> 14940 | S11: =Inputs!E111 -> 9.65 | T11: =Inputs!E116 -> 0.057
B12: =Inputs!F$8 -> KDP | C12: =Inputs!F19*Inputs!F11 -> 38032.8 | D12: =Inputs!F135+Inputs!F127 -> 53478.8 | F12: =Inputs!F25+Inputs!F43-Inputs!F61 -> 15500 | G12: =Inputs!F40+Inputs!F58-Inputs!F76 -> 3738 | H12: =Inputs!F30+Inputs!F48-Inputs!F66 -> 2681 | I12: =Inputs!F37+Inputs!F55-Inputs!F73 -> 1.14 | K12: =Inputs!F99 -> 16425 | L12: =Inputs!F100 -> 4010 | M12: =Inputs!F101 -> 2950 | N12: =Inputs!F102 -> 2.25 | P12: =Inputs!F108 -> 17110 | Q12: =Inputs!F109 -> 4245 | R12: =Inputs!F110 -> 3150 | S12: =Inputs!F111 -> 2.48 | T12: =Inputs!F116 -> 0.042
B13: =Inputs!G$8 -> MNST | C13: =Inputs!G19*Inputs!G11 -> 81081 | D13: =Inputs!G135+Inputs!G127 -> 78091 | F13: =Inputs!G25+Inputs!G43-Inputs!G61 -> 7583 | G13: =Inputs!G40+Inputs!G58-Inputs!G76 -> 2083 | H13: =Inputs!G30+Inputs!G48-Inputs!G66 -> 1976 | I13: =Inputs!G37+Inputs!G55-Inputs!G73 -> 1.52 | K13: =Inputs!G99 -> 8610 | L13: =Inputs!G100 -> 2410 | M13: =Inputs!G101 -> 2240 | N13: =Inputs!G102 -> 1.85 | P13: =Inputs!G108 -> 9340 | Q13: =Inputs!G109 -> 2695 | R13: =Inputs!G110 -> 2510 | S13: =Inputs!G111 -> 2.05 | T13: =Inputs!G116 -> 0.168
B14: =Inputs!H$8 -> CELH | C14: =Inputs!H19*Inputs!H11 -> 16238.352 | D14: =Inputs!H135+Inputs!H127 -> 17155.252 | F14: =Inputs!H25+Inputs!H43-Inputs!H61 -> 1342 | G14: =Inputs!H40+Inputs!H58-Inputs!H76 -> -46 | H14: =Inputs!H30+Inputs!H48-Inputs!H66 -> -79 | I14: =Inputs!H37+Inputs!H55-Inputs!H73 -> 0.36 | K14: =Inputs!H99 -> 3610 | L14: =Inputs!H100 -> 485 | M14: =Inputs!H101 -> 395 | N14: =Inputs!H102 -> 1.15 | P14: =Inputs!H108 -> 4080 | Q14: =Inputs!H109 -> 610 | R14: =Inputs!H110 -> 520 | S14: =Inputs!H111 -> 1.95 | T14: =Inputs!H116 -> 0.362
F16: Last Twelve Months (LTM) | K16: Year 1 Forecast - Calendar Year | P16: Year 2 Forecast - Calendar Year
B17: Ticker | F17: EV / Revenues | G17: EV / EBITDA | H17: EV / EBIT | I17: P/E | K17: EV / Revenues | L17: EV / EBITDA | M17: EV / EBIT | N17: P/E | P17: EV / Revenues | Q17: EV / EBITDA | R17: EV / EBIT | S17: P/E | T17: PEG ratio
B19: =Inputs!E$8 -> PEP | F19: =Inputs!E138/Inputs!E81 -> 2.5996024 | G19: =Inputs!E138/Inputs!E82 -> 13.409234 | H19: =Inputs!E138/Inputs!E83 -> 15.888185 | I19: =Inputs!E11/Inputs!E84 -> 18.3657 | K19: =Inputs!E$138/Inputs!E99 -> 2.4616341 | L19: =Inputs!E$138/Inputs!E100 -> 14.357828 | M19: =Inputs!E$138/Inputs!E101 -> 17.317781 | N19: =Inputs!E133/Inputs!E102 -> 16.644571 | P19: =Inputs!E$138/Inputs!E108 -> 2.368374 | Q19: =Inputs!E$138/Inputs!E109 -> 13.500525 | R19: =Inputs!E$138/Inputs!E110 -> 16.1934 | S19: =Inputs!E133/Inputs!E111 -> 15.092228 | T19: =Inputs!E151/(Inputs!E116*100) -> 2.9201003
B20: =Inputs!F$8 -> KDP | F20: =Inputs!F138/Inputs!F81 -> 3.4502452 | G20: =Inputs!F138/Inputs!F82 -> 14.306795 | H20: =Inputs!F138/Inputs!F83 -> 19.947333 | I20: =Inputs!F11/Inputs!F84 -> 24.175439 | K20: =Inputs!F$138/Inputs!F99 -> 3.2559391 | L20: =Inputs!F$138/Inputs!F100 -> 13.336359 | M20: =Inputs!F$138/Inputs!F101 -> 18.128407 | N20: =Inputs!F133/Inputs!F102 -> 12.248889 | P20: =Inputs!F$138/Inputs!F108 -> 3.1255874 | Q20: =Inputs!F$138/Inputs!F109 -> 12.598068 | R20: =Inputs!F$138/Inputs!F110 -> 16.977397 | S20: =Inputs!F133/Inputs!F111 -> 11.112903 | T20: =Inputs!F151/(Inputs!F116*100) -> 2.9164021
B21: =Inputs!G$8 -> MNST | F21: =Inputs!G138/Inputs!G81 -> 10.298167 | G21: =Inputs!G138/Inputs!G82 -> 37.489678 | H21: =Inputs!G138/Inputs!G83 -> 39.519737 | I21: =Inputs!G11/Inputs!G84 -> 53.881579 | K21: =Inputs!G$138/Inputs!G99 -> 9.0698026 | L21: =Inputs!G$138/Inputs!G100 -> 32.402905 | M21: =Inputs!G$138/Inputs!G101 -> 34.862054 | N21: =Inputs!G133/Inputs!G102 -> 44.27027 | P21: =Inputs!G$138/Inputs!G108 -> 8.3609208 | Q21: =Inputs!G$138/Inputs!G109 -> 28.976252 | R21: =Inputs!G$138/Inputs!G110 -> 31.111952 | S21: =Inputs!G133/Inputs!G111 -> 39.95122 | T21: =Inputs!G151/(Inputs!G116*100) -> 2.6351351
B22: =Inputs!H$8 -> CELH | F22: =Inputs!H138/Inputs!H81 -> 12.783347 | G22: =Inputs!H138/Inputs!H82 -> -372.94026 | H22: =Inputs!H138/Inputs!H83 -> -217.15509 | I22: =Inputs!H11/Inputs!H84 -> 153.11111 | K22: =Inputs!H$138/Inputs!H99 -> 4.7521474 | L22: =Inputs!H$138/Inputs!H100 -> 35.371654 | M22: =Inputs!H$138/Inputs!H101 -> 43.431018 | N22: =Inputs!H133/Inputs!H102 -> 47.930435 | P22: =Inputs!H$138/Inputs!H108 -> 4.2047186 | Q22: =Inputs!H$138/Inputs!H109 -> 28.123364 | R22: =Inputs!H$138/Inputs!H110 -> 32.990869 | S22: =Inputs!H133/Inputs!H111 -> 28.266667 | T22: =Inputs!H151/(Inputs!H116*100) -> 1.3240452
E24: High | F24: =MAX(F19:F22) -> 12.783347 | G24: =MAX(G19:G22) -> 37.489678 | H24: =MAX(H19:H22) -> 39.519737 | I24: =MAX(I19:I22) -> 153.11111 | K24: =MAX(K19:K22) -> 9.0698026 | L24: =MAX(L19:L22) -> 35.371654 | M24: =MAX(M19:M22) -> 43.431018 | N24: =MAX(N19:N22) -> 47.930435 | P24: =MAX(P19:P22) -> 8.3609208 | Q24: =MAX(Q19:Q22) -> 28.976252 | R24: =MAX(R19:R22) -> 32.990869 | S24: =MAX(S19:S22) -> 39.95122 | T24: =MAX(T19:T22) -> 2.9201003
E25: Low | F25: =MIN(F19:F22) -> 2.5996024 | G25: =MIN(G19:G22) -> -372.94026 | H25: =MIN(H19:H22) -> -217.15509 | I25: =MIN(I19:I22) -> 18.3657 | K25: =MIN(K19:K22) -> 2.4616341 | L25: =MIN(L19:L22) -> 13.336359 | M25: =MIN(M19:M22) -> 17.317781 | N25: =MIN(N19:N22) -> 12.248889 | P25: =MIN(P19:P22) -> 2.368374 | Q25: =MIN(Q19:Q22) -> 12.598068 | R25: =MIN(R19:R22) -> 16.1934 | S25: =MIN(S19:S22) -> 11.112903 | T25: =MIN(T19:T22) -> 1.3240452
E26: Median | F26: =MEDIAN(F19:F22) -> 6.8742061 | G26: =MEDIAN(G19:G22) -> 13.858015 | H26: =MEDIAN(H19:H22) -> 17.917759 | I26: =MEDIAN(I19:I22) -> 39.028509 | K26: =MEDIAN(K19:K22) -> 4.0040432 | L26: =MEDIAN(L19:L22) -> 23.380366 | M26: =MEDIAN(M19:M22) -> 26.49523 | N26: =MEDIAN(N19:N22) -> 30.457421 | P26: =MEDIAN(P19:P22) -> 3.665153 | Q26: =MEDIAN(Q19:Q22) -> 20.811944 | R26: =MEDIAN(R19:R22) -> 24.044675 | S26: =MEDIAN(S19:S22) -> 21.679447 | T26: =MEDIAN(T19:T22) -> 2.7757686
E27: Mean | F27: =AVERAGE(F19:F22) -> 7.2828404 | G27: =AVERAGE(G19:G22) -> -76.933638 | H27: =AVERAGE(H19:H22) -> -35.449958 | I27: =AVERAGE(I19:I22) -> 62.383457 | K27: =AVERAGE(K19:K22) -> 4.8848808 | L27: =AVERAGE(L19:L22) -> 23.867186 | M27: =AVERAGE(M19:M22) -> 28.434815 | N27: =AVERAGE(N19:N22) -> 30.273541 | P27: =AVERAGE(P19:P22) -> 4.5149002 | Q27: =AVERAGE(Q19:Q22) -> 20.799552 | R27: =AVERAGE(R19:R22) -> 24.318405 | S27: =AVERAGE(S19:S22) -> 23.605754 | T27: =AVERAGE(T19:T22) -> 2.4489207
E28: EXTR | F28: =F19 -> 2.5996024 | G28: =G19 -> 13.409234 | H28: =H19 -> 15.888185 | I28: =I19 -> 18.3657 | K28: =K19 -> 2.4616341 | L28: =L19 -> 14.357828 | M28: =M19 -> 17.317781 | N28: =N19 -> 16.644571 | P28: =P19 -> 2.368374 | Q28: =Q19 -> 13.500525 | R28: =R19 -> 16.1934 | S28: =S19 -> 15.092228 | T28: =T19 -> 2.9201003

Sheet Inputs
N1: Ticker | O1: Name
A2: Inputs | N2: PEP | O2: PepsiCo.
N3: KDP | O3: Keurig Dr Pepper
N4: MNST | O4: Monster
N5: CELH | O5: Celsius
E7: 1 | F7: 2 | G7: 3 | H7: 4 | I7: 5
A8: Market Data Inputs | C8: Ticker | E8: PEP | F8: KDP | G8: MNST | H8: CELH
C9: Date of latest filing | E9: 10/9/2025(Q3) | F9: 10/28/2025(Q3) | G9: 11/6/2025(Q3) | H9: 11/6/2025 (Q3)
C10: Date of latest fiscal year end (FYE) | E10: 45319 | F10: 45657 | G10: 45657 | H10: 45657
C11: Stock price on current date | E11: 145.64 | F11: 27.56 | G11: 81.9 | H11: 55.12
C12: Share price date | E12: 46048 | F12: 46048 | G12: 46048 | H12: 46048
A15: Shares Data | C15: Basic shares outstanding | E15: 1372 | F15: 1374 | G15: 985 | H15: 258
C16: Net shares from exercisable options | E16: 13 | F16: 6 | G16: 5 | H16: 5
C17: Total shares from convertible debt | E17: 0 | F17: 0 | G17: 0 | H17: 31.6
C18: Total shares from convertible preferred | E18: 0 | F18: 0 | G18: 0 | H18: 0
C19: Fully diluted shares | E19: =SUM(E15:E18) -> 1385 | F19: =SUM(F15:F18) -> 1380 | G19: =SUM(G15:G18) -> 990 | H19: =SUM(H15:H18) -> 294.6
A23: Financials
E24: =E$8 -> PEP | F24: =F$8 -> KDP | G24: =G$8 -> MNST | H24: =H$8 -> CELH | I24: =I$8 -> 0
A25: LAST FISCAL YEAR | C25: Revenues | E25: 91854 | F25: 15350 | G25: 7493 | H25: 1356
C26: COGS | E26: 41744 | F26: 6821 | G26: 3444 | H26: 676
C27: Gross Profit | E27: =E25-E26 -> 50110 | F27: =F25-F26 -> 8529 | G27: =G25-G26 -> 4049 | H27: =H25-H26 -> 680
C28: SG&A | E28: 37190 | F28: 4649 | G28: 2119 | H28: 518
C29: Other Expenses | E29: 33 | F29: 1300 | G29: 0 | H29: 17
C30: EBIT | E30: =E27-E28-E29 -> 12887 | F30: =F27-F28-F29 -> 2580 | G30: =G27-G28-G29 -> 1930 | H30: =H27-H28-H29 -> 145
C31: Interest expense | E31: -935 | F31: -550 | G31: 0 | H31: 0
C32: Non operating income | E32: 350 | F32: 55 | G32: 59 | H32: 22 | J32: =91854+23940-22730 -> 93064
C33: Non operating expense | E33: -352 | F33: -19 | G33: 0 | H33: -43
C34: Pretax income | E34: =SUM(E30:E33) -> 11950 | F34: =SUM(F30:F33) -> 2066 | G34: =SUM(G30:G33) -> 1989 | H34: =SUM(H30:H33) -> 124
C35: Taxes (Benefit) | E35: -2320 | F35: -666 | G35: -146.704 | H35: -19
C36: Net Income | E36: =SUM(E34:E35) -> 9630 | F36: =SUM(F34:F35) -> 1400 | G36: =SUM(G34:G35) -> 1842.296 | H36: =SUM(H34:H35) -> 105
C37: Diluted EPS | E37: 6.95 | F37: 1.05 | G37: 1.49 | H37: 0.45
C39: D&A | E39: -2800 | F39: -1050 | G39: -112 | H39: -32
C40: EBITDA | E40: =E30-E39 -> 15687 | F40: =F30-F39 -> 3630 | G40: =G30-G39 -> 2042 | H40: =H30-H39 -> 177
E42: =E$8 -> PEP | F42: =F$8 -> KDP | G42: =G$8 -> MNST | H42: =H$8 -> CELH | I42: =I$8 -> 0
A43: LAST QUARTER | C43: Revenues | E43: 23940 | F43: 4310 | G43: 2200 | H43: 725
C44: COGS | E44: 11140 | F44: 2155 | G44: 975 | H44: 353
C45: Gross Profit | E45: =E43-E44 -> 12800 | F45: =F43-F44 -> 2155 | G45: =G43-G44 -> 1225 | H45: =H43-H44 -> 372
C46: SG&A | E46: 8600 | F46: 1154 | G46: 549 | H46: 206
C47: Other Expenses | E47: 600 | F47: 2 | G47: 0 | H47: 247
C48: EBIT | E48: =E45-E46-E47 -> 3600 | F48: =F45-F46-F47 -> 999 | G48: =G45-G46-G47 -> 676 | H48: =H45-H46-H47 -> -81
C49: Interest expense | E49: -234 | F49: -138 | G49: -1 | H49: -5
C50: Non operating income | E50: 85 | F50: 14 | G50: 15 | H50: 7
C51: Non operating expense | E51: -1 | F51: -9 | G51: 0 | H51: -2
C52: Pretax income | E52: =SUM(E48:E51) -> 3450 | F52: =SUM(F48:F51) -> 866 | G52: =SUM(G48:G51) -> 690 | H52: =SUM(H48:H51) -> -81
C53: Taxes (Benefit) | E53: -850 | F53: -208 | G53: -165 | H53: 20
C54: Net Income | E54: =SUM(E52:E53) -> 2600 | F54: =SUM(F52:F53) -> 658 | G54: =SUM(G52:G53) -> 525 | H54: =SUM(H52:H53) -> -61
C55: Diluted EPS | E55: 1.9 | F55: 0.49 | G55: 0.53 | H55: 0.24
C57: D&A | E57: -700 | F57: -263 | G57: -31 | H57: -12
C58: EBITDA | E58: =E48-E57 -> 4300 | F58: =F48-F57 -> 1262 | G58: =G48-G57 -> 707 | H58: =H48-H57 -> -69 | I58: *standard
E60: =E$8 -> PEP | F60: =F$8 -> KDP | G60: =G$8 -> MNST | H60: =H$8 -> CELH | I60: =I$8 -> 0
A61: LAST QUARTER MINUS 1 | C61: Revenues | E61: 22730 | F61: 4160 | G61: 2110 | H61: 739
C62: COGS | E62: 10213 | F62: 1862 | G62: 935 | H62: 358
C63: Gross Profit | E63: =E61-E62 -> 12517 | F63: =F61-F62 -> 2298 | G63: =G61-G62 -> 1175 | H63: =H61-H62 -> 381
C64: SG&A | E64: 8950 | F64: 1270 | G64: 545 | H64: 238
C65: Other Expenses | E65: 2307 | F65: 130 | G65: 0 | H65: 0
C66: EBIT | E66: =E63-E64-E65 -> 1260 | F66: =F63-F64-F65 -> 898 | G66: =G63-G64-G65 -> 630 | H66: =H63-H64-H65 -> 143
C67: Interest expense | E67: -235 | F67: -145 | G67: -1 | H67: -5
C68: Non operating income | E68: 70 | F68: 15 | G68: 14 | H68: 2
C69: Non operating expense | E69: -1 | F69: -2 | G69: 0 | H69: -1
C70: Pretax income | E70: =SUM(E66:E69) -> 1094 | F70: =SUM(F66:F69) -> 766 | G70: =SUM(G66:G69) -> 643 | H70: =SUM(H66:H69) -> 139
C71: Taxes (Benefit) | E71: 166 | F71: -219 | G71: -156 | H71: -39
C72: Net Income | E72: =SUM(E70:E71) -> 1260 | F72: =SUM(F70:F71) -> 547 | G72: =SUM(G70:G71) -> 487 | H72: =SUM(H70:H71) -> 100
C73: Diluted EPS | E73: 0.92 | F73: 0.4 | G73: 0.5 | H73: 0.33
C75: D&A | E75: -685 | F75: -256 | G75: -36 | H75: -11
C76: EBITDA | E76: =E66-E75 -> 1945 | F76: =F66-F75 -> 1154 | G76: =G66-G75 -> 666 | H76: =H66-H75 -> 154
C78: LAST TWELVE MONTHS (LTM) | E78: =E$8 -> PEP | F78: =F$8 -> KDP | G78: =G$8 -> MNST | H78: =H$8 -> CELH | I78: =I$8 -> 0
C80: LTM ending date: | E80: 45906 | F80: 45930 | G80: 45930 | H80: 45930
C81: Revenues - LTM | E81: =E25+E43-E61 -> 93064 | F81: =F25+F43-F61 -> 15500 | G81: =G25+G43-G61 -> 7583 | H81: =H25+H43-H61 -> 1342
C82: EBITDA - LTM | E82: =E40+E58-E76 -> 18042 | F82: =F40+F58-F76 -> 3738 | G82: =G40+G58-G76 -> 2083 | H82: =H40+H58-H76 -> -46
C83: EBIT - LTM | E83: =E30+E48-E66 -> 15227 | F83: =F30+F48-F66 -> 2681 | G83: =G30+G48-G66 -> 1976 | H83: =H30+H48-H66 -> -79
C84: EPS - LTM | E84: =E37+E55-E73 -> 7.93 | F84: =F37+F55-F73 -> 1.14 | G84: =G37+G55-G73 -> 1.52 | H84: =H37+H55-H73 -> 0.36
C86: LAST FISCAL YEAR | E86: =E$8 -> PEP | F86: =F$8 -> KDP | G86: =G$8 -> MNST | H86: =H$8 -> CELH | I86: =I$8 -> 0
C88: Year ending date | E88: 45654 | F88: 45657 | G88: 45657 | H88: 45657
C89: Revenues - latest FYE | E89: =E25 -> 91854 | F89: =F25 -> 15350 | G89: =G25 -> 7493 | H89: =H25 -> 1356
C90: EBITDA - latest FYE | E90: =E40 -> 15687 | F90: =F40 -> 3630 | G90: =G40 -> 2042 | H90: =H40 -> 177
C91: EBIT - latest FYE | E91: =E30 -> 12887 | F91: =F30 -> 2580 | G91: =G30 -> 1930 | H91: =H30 -> 145
C92: EPS - latest FYE | E92: =E37 -> 6.95 | F92: =F37 -> 1.05 | G92: =G37 -> 1.49 | H92: =H37 -> 0.45
A94: S&P/CIQ Forecasts
C96: YEAR 1 FORECAST - CALENDAR YEAR | E96: =E$8 -> PEP | F96: =F$8 -> KDP | G96: =G$8 -> MNST | H96: =H$8 -> CELH | I96: =I$8 -> 0
C98: Year ending date | E98: 46387 | F98: 46387 | G98: 46387 | H98: 46387 | I98: 46387
C99: Revenues - Year 1 | E99: 98280 | F99: 16425 | G99: 8610 | H99: 3610
C100: EBITDA - Year 1 | E100: 16850 | F100: 4010 | G100: 2410 | H100: 485
C101: EBIT - Year 1 | E101: 13970 | F101: 2950 | G101: 2240 | H101: 395
C102: EPS - Year 1 | E102: 8.75 | F102: 2.25 | G102: 1.85 | H102: 1.15
C103: Source for estimates: | E103: S&P/CIQ | F103: S&P/CIQ | G103: S&P/CIQ | H103: S&P/CIQ
C105: YEAR 2 FORECAST - CALENDAR YEAR | E105: =E$8 -> PEP | F105: =F$8 -> KDP | G105: =G$8 -> MNST | H105: =H$8 -> CELH | I105: =I$8 -> 0
C107: Year ending date | E107: =EOMONTH(E98,12) -> 46752 | F107: =EOMONTH(F98,12) -> 46752 | G107: =EOMONTH(G98,12) -> 46752 | H107: =EOMONTH(H98,12) -> 46752 | I107: =EOMONTH(I98,12) -> 46752
C108: Revenues - Year 2 | E108: 102150 | F108: 17110 | G108: 9340 | H108: 4080
C109: EBITDA - Year 2 | E109: 17920 | F109: 4245 | G109: 2695 | H109: 610
C110: EBIT - Year 2 | E110: 14940 | F110: 3150 | G110: 2510 | H110: 520
C111: EPS - Year 2 | E111: 9.65 | F111: 2.48 | G111: 2.05 | H111: 1.95
C112: Source for estimates: | E112: S&P/CIQ | F112: S&P/CIQ | G112: S&P/CIQ | H112: S&P/CIQ
C114: LONG TERM (5 YEAR) GROWTH RATE | E114: =E$8 -> PEP | F114: =F$8 -> KDP | G114: =G$8 -> MNST | H114: =H$8 -> CELH | I114: =I$8 -> 0
C116: Long-term growth rate | E116: 0.057 | F116: 0.042 | G116: 0.168 | H116: 0.362
C117: Source for estimates: | E117: S&P/CIQ | F117: S&P/CIQ | G117: S&P/CIQ | H117: S&P/CIQ
C120: Source Document | E120: 10-Q Q3 2025
A121: Balance Sheet Data | C121: ST Data (Incl. current portion) | E121: 6745 | F121: 2285 | G121: 0 | H121: 9
C122: LT debt | E122: 37655 | F122: 13531 | G122: 0 | H122: 861.5
C123: Noncontrolling interests | E123: 138 | F123: 115 | G123: 0 | H123: 0
C124: preferred stock | E124: 0 | F124: 0 | G124: 0 | H124: 852.4
...
